{"cameraMode":{"drawMode":0,"name":"Shaded","section":"Shading Mode"},"sceneLighting":true,"audioPlay":false,"sceneViewState":{"m_AlwaysRefresh":false,"showFog":true,"showSkybox":true,"showFlares":true,"showImageEffects":true,"showParticleSystems":true,"showVisualEffectGraphs":true,"m_FxEnabled":true},"in2DMode":false,"pivot":{"x":-2.601863384246826,"y":-1.7777619361877442,"z":3.562744140625},"rotation":{"x":0.1493910551071167,"y":-0.14039136469364167,"z":0.021433457732200624,"w":0.9785248041152954},"size":9.11514949798584,"orthographic":false}